Metadata-Version: 1.0
Name: pybimaps
Version: 0.2.0
Summary: Various bijective maps in pure python.
Home-page: https://github.com/waipu/pybimaps
Author: waipu
Author-email: waipu@cirno.de
License: GPL3
Keywords: bijective map
Platform: UNKNOWN
